{
    "ingredient": { "type": "item", "code": "game:ingot-*", "name": "metal",
    "allowedVariants": ["copper", "brass", "tinbronze", "bismuthbronze", "blackbronze", "iron", "titanium", "meteoriciron", "steel"] },
    "name": "hingeflangetop",
    "pattern": [[
        "###_###_###",
        "_#___#___#_",
        "#_#_#_#_#_#",
        "_#___#___#_"
    ],
    [
        "#_# #_#_#_#",
        "_#___#___#_",
        "___________",
        "___________"
    ]
],
    "output": { "type": "item", "code": "hammersringingfall:hingeflangetop-{metal}", "stacksize": 3}
}
